{
  "StartInOrbit": true,
  "ScheduledLaunchTime": "1968-12-21T07:51:00",
  "InitialTimeToRetrograde": "11:20:00",
  "MissionCommands": [
    {
      "Delivered": false,
      "Completed": false,
      "Priority": false,
      "Action": 0,
      "Timestamp": 10.0,
      "DisplayTime": 5.0,
      "From": 2,
      "Message": "Welcome to Part IV of the Apollo 8 campaign. This mission has not yet been developed.",
      "Value1": 0.0,
      "Value2": 0.0,
      "Value3": 0.0,
      "String1": null,
      "String2": null,
      "String3": null,
      "Bool1": false,
      "ThresholdLimit": 0.0,
      "PinID": 0,
      "PinPosition": 0,
      "KnobID": 0,
      "ButtonId": 0,
      "FuseID": 0,
      "FusePosition": 0,
      "Fault": 0,
      "PlayAudioClip_String3": false
    }
  ],
  "MissionGoals": [
    {
      "Progress": null,
      "Completed": false,
      "Type": 0,
      "Description": "Complete the mission chapter.",
      "Target1": 0.0,
      "Target2": 0.0,
      "Target3": 0.0,
      "String1": null,
      "String2": null
    }
  ],
  "MissionActivities": [],
  "SpaceProgram": 2,
  "Id": 503,
  "Title": "Apollo 8: Part IV",
  "Description": "The Apollo 8 crew is now in a Lunar Orbit.",
  "BriefingText": "BRIEFING\r\n\r\nApollo 8 is GO for launch.",
  "FlightPlanPrefabId": 0,
  "MinutesBeforeLaunch": 60.0,
  "TargetAp": 185.0,
  "TargetPe": 185.0,
  "Inclination": 32.5,
  "CommandModulePilot": "Lovell",
  "LunarModulePilot": "Anders",
  "DisableDefaultAudioSFX": true,
  "LoadState": "part4_state.rsg",
  "Payload": 0
}